argparse_interface-0.3.1.dist-info/licenses/LICENSE
argui/Demo.py
argui/Interface.py
argui/Logging.py
argui/ParserGroup.py
argui/ParserMap.py
argui/ReturnCodes.py
argui/Utils.py
argui/Wrapper.py
argui/__init__.py
argui/debug/ExportDOM.py
argui/debug/__init__.py
argui/modals/AlertModal.py
argui/modals/FileSelectModal.py
argui/modals/QuitModal.py
argui/modals/SubmitErrorModal.py
argui/modals/SubmitModal.py
argui/modals/__init__.py
argui/style/AlertModal.tcss
argui/style/FileSelectModal.tcss
argui/style/Interface.tcss
argui/style/SubmitErrorModal.tcss
argui/types/FileSelectDir.py
argui/types/FileSelectFile.py
argui/types/MetaType.py
argui/types/__init__.py
argui/widgets/FileSelect.py
argui/widgets/InputBuilders.py
argui/widgets/InputList.py
argui/widgets/__init__.py
argparse_interface-0.3.1.dist-info/METADATA
argparse_interface-0.3.1.dist-info/WHEEL
argparse_interface-0.3.1.dist-info/entry_points.txt
argparse_interface-0.3.1.dist-info/top_level.txt
argparse_interface-0.3.1.dist-info/RECORD
