Metadata-Version: 2.4
Name: argparse-interface
Version: 0.3.1
Summary: An automatic, terminal based interactive interface for any Python 3 `argparse` command line with keyboard and mouse support.
Author: Sorcerio
License-Expression: MIT
Classifier: Programming Language :: Python :: 3
Classifier: Operating System :: OS Independent
Requires-Python: >=3.10
License-File: LICENSE
Requires-Dist: textual==1.0
Requires-Dist: textual-dev==1.7
Dynamic: license-file
